ai_compat/__init__.py
ai_compat/checker.py
ai_compat/cli.py
ai_compat/exporter.py
ai_compat/fixer.py
ai_compat/gpu.py
ai_compat/scanner.py
ai_compat/tester.py
ai_compat/tpu.py
ai_compat/rules/cuda_rules.json
ai_compat/rules/pytorch_rules.json
ai_compat/rules/tensorflow_rules.json
ai_compat/rules/tpu_rules.json
ai_compat-0.3.0.dist-info/METADATA
ai_compat-0.3.0.dist-info/WHEEL
ai_compat-0.3.0.dist-info/entry_points.txt
ai_compat-0.3.0.dist-info/top_level.txt
ai_compat-0.3.0.dist-info/RECORD
