Metadata-Version: 2.4
Name: ai-compat
Version: 0.3.0
Summary: GPU and TPU compatibility toolkit for AI frameworks
Author: PyLib Contributors
License: MIT
Project-URL: Homepage, https://github.com/upendra-manike/PyLib
Project-URL: Repository, https://github.com/upendra-manike/PyLib
Keywords: gpu,tpu,cuda,ai,pytorch,tensorflow,onnx,compatibility,cloud-tpu,edge-tpu
Classifier: Topic :: Scientific/Engineering :: Artificial Intelligence
Classifier: Topic :: System :: Hardware :: Hardware Drivers
Classifier: Intended Audience :: Developers
Classifier: License :: OSI Approved :: MIT License
Classifier: Programming Language :: Python :: 3
Classifier: Programming Language :: Python :: 3.8
Classifier: Programming Language :: Python :: 3.9
Classifier: Programming Language :: Python :: 3.10
Classifier: Programming Language :: Python :: 3.11
Classifier: Programming Language :: Python :: 3.12
Requires-Python: >=3.8
